netdriver/agent/__init__.py
netdriver/agent/api/__init__.py
netdriver/agent/api/rest/__init__.py
netdriver/agent/api/rest/v0/__init__.py
netdriver/agent/api/rest/v1/__init__.py
netdriver/agent/api/rest/v1/api.py
netdriver/agent/api/rpc/__init__.py
netdriver/agent/containers.py
netdriver/agent/handlers/__init__.py
netdriver/agent/handlers/cmd_req_handler.py
netdriver/agent/handlers/conn_req_handler.py
netdriver/agent/handlers/error_handlers.py
netdriver/agent/main.py
netdriver/agent/models/__init__.py
netdriver/agent/models/cmd.py
netdriver/agent/models/common.py
netdriver/agent/models/conn.py
netdriver/agent/models/header.py
netdriver/agent/route.py
netdriver/simunet/__init__.py
netdriver/simunet/containers.py
netdriver/simunet/main.py
netdriver/client/__init__.py
netdriver/client/channel.py
netdriver/client/merger.py
netdriver/client/mode.py
netdriver/client/pool.py
netdriver/client/session.py
netdriver/client/task.py
netdriver/exception/__init__.py
netdriver/exception/error_code.py
netdriver/exception/errors.py
netdriver/exception/server.py
netdriver/log/__init__.py
netdriver/log/logman.py
netdriver/plugin/__init__.py
netdriver/plugin/core.py
netdriver/plugin/engine.py
netdriver/plugin/plugin_info.py
netdriver/plugin/types.py
netdriver/plugins/__init__.py
netdriver/plugins/arista/__init__.py
netdriver/plugins/arista/arista.py
netdriver/plugins/arista/arista_eos.py
netdriver/plugins/array/__init__.py
netdriver/plugins/array/array.py
netdriver/plugins/array/array_ag.py
netdriver/plugins/base.py
netdriver/plugins/chaitin/__init__.py
netdriver/plugins/chaitin/chaitin.py
netdriver/plugins/chaitin/chaitin_ctdsg.py
netdriver/plugins/check_point/__init__.py
netdriver/plugins/check_point/check_point.py
netdriver/plugins/check_point/check_point_security_gateway.py
netdriver/plugins/cisco/__init__.py
netdriver/plugins/cisco/cisco.py
netdriver/plugins/cisco/cisco_asa.py
netdriver/plugins/cisco/cisco_asr.py
netdriver/plugins/cisco/cisco_catalyst.py
simunet_netdriver-0.1.19.dist-info/LICENSE
simunet_netdriver-0.1.19.dist-info/METADATA
simunet_netdriver-0.1.19.dist-info/WHEEL
simunet_netdriver-0.1.19.dist-info/entry_points.txt
simunet_netdriver-0.1.19.dist-info/RECORD
